LICENSE
MANIFEST.in
distribute_setup.py
requirements.pip
setup.py
redique/__init__.py
redique/queue.py
redique.egg-info/PKG-INFO
redique.egg-info/SOURCES.txt
redique.egg-info/dependency_links.txt
redique.egg-info/not-zip-safe
redique.egg-info/requires.txt
redique.egg-info/top_level.txt
redique/tests/__init__.py
redique/tests/test_basics.py