Metadata-Version: 1.0
Name: redique
Version: 0.1.1
Summary: A super easy Queued RPC on top of Redis
Home-page: https://github.com/AhmedSoliman/redique
Author: Ahmed Soliman
Author-email: me@ahmedsoliman.com
License: MIT
Platform: UNKNOWN
Classifier: Development Status :: 4 - Beta
Classifier: Intended Audience :: Developers
Classifier: Intended Audience :: System Administrators
Classifier: License :: OSI Approved :: MIT License
Classifier: Operating System :: OS Independent
Classifier: Programming Language :: Python :: 2.6
Classifier: Programming Language :: Python :: 2.7
